evidence_theory/__init__.py
evidence_theory/core/__init__.py
evidence_theory/core/atom.py
evidence_theory/core/distribution.py
evidence_theory/element/__init__.py
evidence_theory/element/combination.py
evidence_theory/element/permutation.py
evidence_theory/evpiece/__init__.py
evidence_theory/evpiece/dual.py
evidence_theory/evpiece/single.py
evidence_theory/math/__init__.py
evidence_theory/math/func.py
evidence_theory/math/stat/__init__.py
evidence_theory/math/stat/distribution.py
evidence_theory/math/stat/moment.py
evidence_thoery-0.0.13.dist-info/LICENSE
evidence_thoery-0.0.13.dist-info/METADATA
evidence_thoery-0.0.13.dist-info/WHEEL
evidence_thoery-0.0.13.dist-info/top_level.txt
evidence_thoery-0.0.13.dist-info/RECORD
