Metadata-Version: 2.1
Name: evidence_thoery
Version: 0.0.13
Summary: A python package of evidence theory
Author-email: Tianxiang Zhan <zhantianxianguestc@hotmail.com>
Project-URL: homepage, https://github.com/ztxtech/evidence_theory
Project-URL: repository, https://github.com/ztxtech/evidence_theory.git
Classifier: Programming Language :: Python :: 3
Classifier: License :: OSI Approved :: MIT License
Classifier: Operating System :: OS Independent
Requires-Python: >=3.7
License-File: LICENSE
